netemu/__init__.py
netemu/__main__.py
netemu/cli.py
netemu/command.py
netemu/core.py
netemu/state.py
netemu-0.0.7.dist-info/entry_points.txt
netemu-0.0.7.dist-info/LICENSE
netemu-0.0.7.dist-info/WHEEL
netemu-0.0.7.dist-info/METADATA
netemu-0.0.7.dist-info/RECORD
