Metadata-Version: 2.1
Name: netemu
Version: 0.0.7
Summary: A lightweight, rootless network emulator for Linux.
Author-email: Luís Fonseca <luis@lhf.pt>
Requires-Python: >=3.6
Classifier: License :: OSI Approved :: GNU General Public License v3 or later (GPLv3+)
Project-URL: Home, https://github.com/luishfonseca/netemu
